{"config": {"A3": "king_w", "A6": "pawn_w", "A8": "bishop_b", "B2": "king_w", "B3": "rook_w", "B6": "rook_w", "C2": "queen_w", "C5": "rook_w", "C8": "bishop_b", "D1": "rook_w", "D2": "rook_b", "D3": "rook_w", "D5": "queen_w", "D6": "king_b", "D7": "bishop_w", "D8": "queen_w", "E2": "rook_b", "E4": "king_w", "E6": "knight_w", "E7": "king_b", "F2": "queen_b", "F3": "bishop_b", "F4": "knight_b", "F5": "bishop_b", "F7": "pawn_w", "G1": "pawn_b", "G2": "knight_b", "G3": "queen_b", "G4": "rook_b", "G5": "king_b", "G8": "rook_b", "H1": "king_w", "H5": "rook_w", "H6": "bishop_w", "H7": "pawn_b"}, "corners": [[0.5548273921012878, 0.7827776074409485], [0.8223633170127869, 0.45308130979537964], [0.18718037009239197, 0.5489751696586609], [0.4336848258972168, 0.16869157552719116]]}