{"config": {"A1": "queen_w", "A3": "king_w", "A8": "rook_b", "B1": "bishop_w", "B4": "king_b", "C1": "pawn_b", "C2": "queen_b", "C6": "knight_w", "C7": "rook_b", "C8": "knight_w", "D1": "rook_b", "D2": "queen_w", "D3": "bishop_w", "D5": "rook_b", "D7": "queen_w", "D8": "pawn_b", "E1": "pawn_b", "E2": "king_w", "E3": "queen_w", "E4": "pawn_w", "E5": "knight_b", "F1": "bishop_w", "F2": "king_b", "F3": "knight_b", "G1": "king_w", "G4": "king_b", "G5": "pawn_w", "H3": "king_w", "H4": "pawn_b", "H6": "rook_w"}, "corners": [[0.7707594037055969, 0.47941431403160095], [0.47802838683128357, 0.22132501006126404], [0.5199424028396606, 0.7583836913108826], [0.2304498553276062, 0.5209370255470276]]}