{"config": {"A3": "bishop_b", "A4": "king_b", "A6": "rook_b", "B1": "rook_w", "B2": "rook_w", "B6": "king_w", "C1": "pawn_w", "C2": "bishop_b", "C3": "queen_w", "C7": "knight_b", "C8": "pawn_b", "D4": "knight_w", "D5": "king_b", "D7": "king_b", "D8": "rook_b", "E3": "queen_b", "E6": "knight_w", "E7": "king_b", "E8": "king_w", "F2": "queen_w", "F6": "pawn_b", "G1": "king_w", "G4": "pawn_w", "G5": "knight_w", "H1": "pawn_b", "H3": "pawn_w", "H6": "pawn_w"}, "corners": [[0.24210225045681, 0.33081933856010437], [0.33797958493232727, 0.7450950741767883], [0.672092616558075, 0.24059155583381653], [0.7492068409919739, 0.6628948450088501]]}