{"config": {"A2": "king_b", "A3": "queen_w", "A4": "pawn_w", "A6": "bishop_w", "B4": "knight_b", "B5": "rook_w", "B6": "knight_w", "B7": "king_w", "B8": "rook_b", "D1": "queen_w", "D2": "pawn_b", "D3": "knight_b", "D7": "king_b", "E1": "queen_b", "E3": "queen_w", "E7": "knight_w", "F1": "queen_w", "F4": "bishop_b", "F5": "bishop_b", "F6": "king_b", "G6": "rook_b", "G7": "pawn_w", "G8": "king_b", "H1": "queen_b", "H2": "king_b", "H5": "king_b", "H7": "queen_b"}, "corners": [[0.7779728770256042, 0.24967293441295624], [0.24472589790821075, 0.22089648246765137], [0.7273349165916443, 0.7430482506752014], [0.24973638355731964, 0.7280282378196716]]}