{"config": {"A1": "king_w", "A2": "king_b", "A3": "pawn_w", "A6": "rook_w", "A8": "bishop_b", "B3": "pawn_b", "B6": "pawn_b", "C1": "bishop_w", "C2": "rook_w", "C5": "queen_w", "C6": "king_w", "C7": "rook_w", "C8": "king_w", "D3": "queen_w", "D4": "bishop_b", "D6": "knight_b", "D7": "bishop_w", "D8": "rook_w", "E1": "rook_b", "E5": "rook_w", "F1": "queen_w", "F4": "rook_b", "F5": "king_w", "F7": "pawn_w", "G2": "queen_b", "G4": "king_b", "G5": "pawn_b", "G7": "king_w", "H1": "rook_w", "H6": "knight_w"}, "corners": [[0.473835825920105, 0.8027710914611816], [0.8347858786582947, 0.5266316533088684], [0.1603289097547531, 0.4724405109882355], [0.5300584435462952, 0.14516420662403107]]}