{"config": {"A1": "queen_b", "A2": "rook_b", "A3": "knight_w", "A5": "queen_w", "A7": "queen_b", "A8": "bishop_w", "B3": "rook_b", "B4": "knight_w", "B5": "pawn_w", "B8": "bishop_w", "C3": "queen_w", "C5": "queen_b", "C6": "pawn_b", "C7": "pawn_b", "C8": "bishop_w", "E1": "queen_b", "E3": "pawn_w", "E4": "rook_w", "E5": "king_w", "E7": "queen_b", "E8": "pawn_w", "F2": "king_w", "F4": "bishop_w", "F5": "rook_w", "F8": "knight_b", "G1": "knight_w", "G3": "rook_b", "G5": "rook_w", "G8": "king_b", "H3": "king_w", "H4": "rook_w", "H6": "king_b"}, "corners": [[0.7477616667747498, 0.22097663581371307], [0.2080245018005371, 0.2689605951309204], [0.7592567801475525, 0.7051517963409424], [0.2850038707256317, 0.742122232913971]]}