{"config": {"A3": "king_b", "A4": "king_w", "A6": "knight_b", "A8": "queen_b", "B1": "rook_b", "B2": "bishop_b", "B3": "pawn_b", "B4": "king_b", "B5": "rook_b", "B8": "rook_b", "C4": "bishop_w", "C5": "bishop_w", "C7": "bishop_b", "C8": "king_b", "D2": "bishop_b", "D6": "rook_b", "D7": "pawn_b", "D8": "rook_b", "E2": "bishop_w", "E3": "queen_b", "E4": "rook_b", "E5": "knight_b", "E6": "bishop_w", "E7": "pawn_b", "F1": "queen_w", "F2": "knight_w", "G1": "king_b", "G6": "pawn_b", "G7": "pawn_b", "H6": "rook_b"}, "corners": [[0.698698878288269, 0.7940654158592224], [0.8430992364883423, 0.28428733348846436], [0.18678376078605652, 0.6962235569953918], [0.26955047249794006, 0.16016477346420288]]}