{"config": {"A4": "pawn_b", "A6": "queen_w", "A7": "king_b", "B1": "king_b", "B3": "pawn_w", "B5": "knight_w", "C3": "king_w", "C6": "pawn_w", "C7": "pawn_w", "D1": "pawn_w", "D3": "queen_b", "D4": "rook_w", "E1": "queen_b", "E2": "pawn_w", "E6": "bishop_w", "E8": "pawn_w", "F1": "rook_b", "F2": "king_w", "F4": "pawn_w", "F8": "pawn_w", "G2": "queen_w", "G4": "rook_b", "H1": "queen_w", "H2": "queen_w", "H4": "rook_b", "H5": "bishop_w", "H6": "king_b", "H7": "king_b", "H8": "pawn_b"}, "corners": [[0.8430915474891663, 0.3148432970046997], [0.3102681636810303, 0.1535053551197052], [0.6716066002845764, 0.8134148716926575], [0.17525875568389893, 0.6752811670303345]]}