{"config": {"A2": "knight_b", "A4": "bishop_b", "A8": "king_w", "B1": "king_w", "B3": "bishop_w", "B4": "bishop_b", "B5": "king_w", "B6": "pawn_w", "C1": "pawn_b", "C2": "knight_b", "C4": "knight_b", "C6": "king_w", "C7": "bishop_w", "C8": "queen_w", "D1": "pawn_w", "D2": "pawn_w", "D5": "rook_w", "D6": "rook_w", "D7": "pawn_b", "E1": "queen_w", "E2": "pawn_b", "E4": "knight_w", "E6": "bishop_w", "E7": "king_w", "E8": "bishop_w", "F2": "bishop_w", "F5": "queen_b", "F6": "pawn_b", "F7": "bishop_b", "G1": "bishop_b", "G2": "bishop_w", "G7": "knight_b", "H2": "knight_b", "H4": "rook_b", "H5": "bishop_w", "H7": "knight_b"}, "corners": [[0.7753996253013611, 0.6095360517501831], [0.6113614439964294, 0.2192905694246292], [0.39107102155685425, 0.7732622027397156], [0.22089409828186035, 0.3895188868045807]]}