{"config": {"A5": "pawn_w", "A6": "king_w", "A7": "queen_b", "B1": "king_w", "B3": "pawn_b", "B4": "knight_b", "B5": "bishop_b", "B8": "rook_w", "C1": "rook_w", "C2": "bishop_w", "C5": "knight_w", "C6": "king_w", "C7": "bishop_b", "D2": "king_w", "D3": "rook_b", "D4": "queen_b", "D6": "pawn_w", "E3": "bishop_b", "E4": "king_w", "E6": "knight_b", "E8": "king_b", "F1": "king_w", "F2": "knight_w", "F8": "queen_b", "G1": "knight_b", "G2": "pawn_b", "G4": "rook_b", "G7": "rook_b", "G8": "bishop_b", "H4": "queen_b", "H5": "bishop_w", "H7": "pawn_w"}, "corners": [[0.31181851029396057, 0.624735951423645], [0.6296153664588928, 0.6735199689865112], [0.34880387783050537, 0.29758545756340027], [0.7097033858299255, 0.3610004186630249]]}