{"config": {"A1": "bishop_b", "A2": "queen_w", "A4": "bishop_w", "A5": "queen_b", "A6": "knight_b", "A8": "king_w", "B1": "rook_w", "B2": "queen_w", "B5": "bishop_w", "B6": "knight_w", "C1": "rook_b", "C2": "rook_b", "C3": "king_b", "C5": "knight_b", "D1": "queen_w", "D4": "king_w", "D7": "rook_b", "D8": "queen_w", "E2": "rook_w", "E4": "queen_b", "E5": "bishop_w", "E7": "queen_b", "E8": "bishop_w", "F2": "king_b", "F7": "pawn_w", "F8": "rook_w", "G2": "knight_w", "G5": "bishop_w", "G6": "pawn_w", "H4": "queen_b", "H6": "rook_w"}, "corners": [[0.12492094188928604, 0.5608487129211426], [0.5598036646842957, 0.8651989102363586], [0.4369175136089325, 0.11476366221904755], [0.8783599138259888, 0.43861904740333557]]}