{"config": {"A1": "bishop_w", "A3": "king_w", "A4": "queen_w", "A8": "pawn_b", "B3": "queen_w", "B4": "knight_b", "B6": "knight_w", "B7": "rook_b", "C2": "pawn_b", "C8": "rook_w", "D1": "pawn_w", "D2": "king_w", "D4": "bishop_b", "D6": "king_w", "D7": "bishop_w", "E2": "queen_w", "E6": "rook_b", "E8": "knight_w", "F1": "knight_w", "F5": "king_w", "F7": "rook_w", "G7": "pawn_b", "G8": "knight_w", "H2": "pawn_b", "H3": "rook_b", "H5": "king_b", "H8": "rook_b"}, "corners": [[0.44783639907836914, 0.23398037254810333], [0.24863643944263458, 0.5423054695129395], [0.759226381778717, 0.45637911558151245], [0.5438162088394165, 0.7233613133430481]]}