{"config": {"A1": "pawn_b", "A2": "knight_w", "A4": "king_w", "A7": "queen_w", "B2": "knight_b", "B3": "knight_w", "B5": "knight_w", "B6": "king_w", "C2": "bishop_b", "C4": "knight_b", "C5": "king_b", "C6": "knight_b", "C7": "knight_b", "C8": "pawn_b", "D1": "bishop_b", "D3": "king_b", "D6": "rook_b", "D7": "rook_b", "D8": "knight_w", "E2": "pawn_b", "E5": "bishop_b", "E8": "pawn_w", "F2": "king_w", "F3": "knight_w", "G1": "pawn_w", "G2": "rook_w", "G6": "king_b", "H3": "pawn_b", "H4": "king_b", "H7": "king_b"}, "corners": [[0.23115962743759155, 0.36318373680114746], [0.3718399107456207, 0.7254775762557983], [0.6503878235816956, 0.23542076349258423], [0.7467184662818909, 0.6255570650100708]]}