{"config": {"A2": "pawn_w", "A3": "knight_b", "A6": "king_w", "B2": "queen_w", "B4": "king_b", "B5": "pawn_b", "B7": "queen_b", "C1": "bishop_b", "C2": "pawn_w", "C3": "bishop_w", "D2": "king_b", "D3": "rook_b", "D4": "king_b", "E2": "king_w", "E3": "king_w", "E4": "bishop_w", "E6": "rook_w", "F2": "queen_b", "F3": "pawn_b", "F5": "bishop_b", "F6": "pawn_b", "F8": "king_w", "G3": "queen_w", "G8": "rook_w", "H1": "rook_b", "H2": "king_b", "H3": "pawn_b", "H4": "bishop_w", "H6": "queen_b", "H8": "knight_b"}, "corners": [[0.7630740404129028, 0.3615705072879791], [0.34962567687034607, 0.24033841490745544], [0.6264593601226807, 0.7183776497840881], [0.26103830337524414, 0.6257624626159668]]}