{"config": {"A1": "bishop_b", "A6": "king_b", "B1": "knight_b", "B4": "queen_b", "B5": "rook_w", "B6": "knight_b", "B7": "queen_b", "B8": "rook_b", "C1": "knight_w", "C4": "rook_w", "C5": "rook_b", "C7": "rook_w", "C8": "pawn_b", "D1": "queen_w", "D2": "knight_w", "D3": "king_w", "D5": "pawn_b", "D7": "pawn_w", "E2": "knight_b", "E3": "queen_b", "E5": "queen_w", "E8": "queen_w", "F2": "pawn_b", "F5": "queen_w", "F6": "pawn_w", "F7": "king_w", "F8": "pawn_b", "G1": "pawn_w", "G2": "pawn_b", "G5": "pawn_w", "G6": "knight_w", "H2": "king_b", "H5": "pawn_w", "H7": "knight_b"}, "corners": [[0.2692560851573944, 0.6691643595695496], [0.6734623908996582, 0.7189276218414307], [0.3040473163127899, 0.2526860535144806], [0.7532033324241638, 0.3143728971481323]]}