{"config": {"A1": "rook_w", "A3": "knight_w", "A5": "queen_w", "A8": "bishop_b", "B3": "king_b", "B5": "queen_w", "B6": "rook_b", "B7": "pawn_w", "C1": "knight_b", "C3": "knight_b", "C4": "king_b", "C6": "king_b", "C7": "rook_w", "D1": "pawn_b", "D3": "king_b", "D4": "knight_w", "D5": "knight_b", "D7": "bishop_b", "D8": "queen_w", "E4": "knight_b", "E5": "rook_b", "F1": "pawn_w", "F2": "rook_w", "F3": "queen_b", "F8": "bishop_b", "G2": "king_w", "G3": "bishop_b", "G4": "bishop_w", "G5": "bishop_w", "G8": "king_w", "H2": "bishop_w", "H3": "bishop_b", "H4": "bishop_b", "H5": "king_w"}, "corners": [[0.4584643542766571, 0.2679230570793152], [0.26921969652175903, 0.5412907600402832], [0.7311832308769226, 0.4586372673511505], [0.5411325693130493, 0.7298252582550049]]}