{"config": {"A2": "queen_w", "A4": "king_b", "A5": "knight_b", "B1": "rook_w", "B3": "rook_w", "B6": "rook_w", "B8": "knight_b", "C3": "king_w", "C4": "bishop_b", "C5": "bishop_b", "C6": "bishop_w", "C7": "rook_w", "C8": "queen_w", "D5": "queen_b", "D6": "king_b", "D7": "rook_b", "E1": "queen_w", "E3": "knight_w", "E6": "queen_w", "E7": "queen_b", "F1": "rook_w", "F3": "queen_w", "F4": "queen_w", "F5": "pawn_w", "F8": "king_w", "G1": "pawn_w", "G2": "pawn_b", "G4": "bishop_w", "G5": "pawn_w", "G6": "king_b", "G7": "pawn_b", "G8": "pawn_w", "H1": "rook_b", "H2": "rook_w", "H3": "queen_b", "H5": "knight_w", "H8": "knight_b"}, "corners": [[0.5804122686386108, 0.8496751189231873], [0.8798762559890747, 0.4195607304573059], [0.12872743606567383, 0.5786047577857971], [0.4105691909790039, 0.11122967302799225]]}