{"config": {"A1": "pawn_w", "A2": "bishop_b", "A3": "queen_w", "A7": "bishop_b", "B2": "knight_w", "B3": "bishop_w", "B6": "pawn_w", "B7": "pawn_b", "C1": "king_w", "C2": "king_b", "C4": "king_w", "C6": "pawn_w", "C7": "pawn_w", "C8": "king_w", "D1": "king_b", "D4": "bishop_b", "D7": "pawn_b", "E1": "knight_b", "E2": "knight_w", "E4": "pawn_b", "E6": "king_b", "E7": "rook_w", "F1": "king_b", "F2": "bishop_w", "F3": "bishop_b", "F4": "pawn_b", "F6": "queen_w", "F8": "rook_w", "G1": "rook_b", "G2": "bishop_b", "G4": "knight_w", "G5": "king_b", "G7": "knight_b", "H1": "rook_b", "H2": "queen_b", "H3": "knight_w", "H4": "queen_b"}, "corners": [[0.37843024730682373, 0.7848967909812927], [0.7990003228187561, 0.6226417422294617], [0.18799437582492828, 0.3720252513885498], [0.634598433971405, 0.18456770479679108]]}