{"config": {"A1": "knight_b", "A2": "pawn_b", "A4": "queen_b", "A5": "rook_w", "A6": "knight_b", "A7": "bishop_b", "B3": "king_w", "B4": "king_w", "B5": "pawn_b", "B7": "knight_b", "C6": "bishop_b", "C8": "queen_w", "D1": "king_w", "D5": "queen_w", "D6": "bishop_b", "D8": "bishop_w", "E1": "queen_b", "E4": "king_w", "E6": "bishop_b", "E8": "pawn_b", "F4": "bishop_b", "F6": "king_w", "F7": "pawn_w", "G1": "pawn_b", "G2": "king_b", "G3": "knight_w", "G6": "rook_w", "G8": "queen_b", "H5": "rook_b", "H6": "queen_w", "H7": "knight_b"}, "corners": [[0.12536628544330597, 0.46852120757102966], [0.45567798614501953, 0.8686015605926514], [0.5414671897888184, 0.1194278672337532], [0.8787648677825928, 0.5296017527580261]]}